{"117": {"id": "117", "title": "Bayern Munich", "history": [{"h_a": "a", "xG": 2.91794, "xGA": 1.98777, "npxG": 2.91794, "npxGA": 1.98777, "ppda": {"att": 154, "def": 18}, "ppda_allowed": {"att": 365, "def": 33}, "deep": 17, "deep_allowed": 7, "scored": 1, "missed": 1, "xpts": 1.9867, "result": "d", "date": "2021-08-13 18:30:00", "wins": 0, "draws": 1, "loses": 0, "pts": 1, "npxGD": 0.9301700000000002}]}, "119": {"id": "119", "title": "Bayer Leverkusen", "history": [{"h_a": "a", "xG": 0.7943, "xGA": 0.443841, "npxG": 0.7943, "npxGA": 0.443841, "ppda": {"att": 172, "def": 24}, "ppda_allowed": {"att": 437, "def": 24}, "deep": 5, "deep_allowed": 6, "scored": 1, "missed": 1, "xpts": 1.6247, "result": "d", "date": "2021-08-14 13:30:00", "wins": 0, "draws": 1, "loses": 0, "pts": 1, "npxGD": 0.350459}]}, "120": {"id": "120", "title": "Hoffenheim", "history": [{"h_a": "a", "xG": 3.44423, "xGA": 0.734658, "npxG": 3.44423, "npxGA": 0.734658, "ppda": {"att": 206, "def": 20}, "ppda_allowed": {"att": 258, "def": 13}, "deep": 8, "deep_allowed": 9, "scored": 4, "missed": 0, "xpts": 2.8663999999999996, "result": "w", "date": "2021-08-14 13:30:00", "wins": 1, "draws": 0, "loses": 0, "pts": 3, "npxGD": 2.709572}]}, "121": {"id": "121", "title": "Augsburg", "history": [{"h_a": "h", "xG": 0.734658, "xGA": 3.44423, "npxG": 0.734658, "npxGA": 3.44423, "ppda": {"att": 258, "def": 13}, "ppda_allowed": {"att": 206, "def": 20}, "deep": 9, "deep_allowed": 8, "scored": 0, "missed": 4, "xpts": 0.0863, "result": "l", "date": "2021-08-14 13:30:00", "wins": 0, "draws": 0, "loses": 1, "pts": 0, "npxGD": -2.709572}]}, "122": {"id": "122", "title": "Hertha Berlin", "history": [{"h_a": "a", "xG": 2.1078, "xGA": 1.62567, "npxG": 2.1078, "npxGA": 1.62567, "ppda": {"att": 242, "def": 17}, "ppda_allowed": {"att": 170, "def": 33}, "deep": 4, "deep_allowed": 8, "scored": 1, "missed": 3, "xpts": 1.7875, "result": "l", "date": "2021-08-15 15:30:00", "wins": 0, "draws": 0, "loses": 1, "pts": 0, "npxGD": 0.48213000000000017}]}, "125": {"id": "125", "title": "Mainz 05", "history": [{"h_a": "h", "xG": 1.27109, "xGA": 0.841814, "npxG": 1.27109, "npxGA": 0.841814, "ppda": {"att": 301, "def": 18}, "ppda_allowed": {"att": 106, "def": 23}, "deep": 2, "deep_allowed": 6, "scored": 1, "missed": 0, "xpts": 1.8362, "result": "w", "date": "2021-08-15 13:30:00", "wins": 1, "draws": 0, "loses": 0, "pts": 3, "npxGD": 0.4292760000000001}]}, "129": {"id": "129", "title": "Borussia Dortmund", "history": [{"h_a": "h", "xG": 2.83799, "xGA": 1.36709, "npxG": 2.83799, "npxGA": 1.36709, "ppda": {"att": 219, "def": 14}, "ppda_allowed": {"att": 411, "def": 31}, "deep": 17, "deep_allowed": 1, "scored": 5, "missed": 2, "xpts": 2.3218, "result": "w", "date": "2021-08-14 16:30:00", "wins": 1, "draws": 0, "loses": 0, "pts": 3, "npxGD": 1.4709}]}, "130": {"id": "130", "title": "Borussia M.Gladbach", "history": [{"h_a": "h", "xG": 1.98777, "xGA": 2.91794, "npxG": 1.98777, "npxGA": 2.91794, "ppda": {"att": 365, "def": 33}, "ppda_allowed": {"att": 154, "def": 18}, "deep": 7, "deep_allowed": 17, "scored": 1, "missed": 1, "xpts": 0.8086, "result": "d", "date": "2021-08-13 18:30:00", "wins": 0, "draws": 1, "loses": 0, "pts": 1, "npxGD": -0.9301700000000002}]}, "131": {"id": "131", "title": "Wolfsburg", "history": [{"h_a": "h", "xG": 2.78774, "xGA": 0.297792, "npxG": 2.02997, "npxGA": 0.297792, "ppda": {"att": 166, "def": 17}, "ppda_allowed": {"att": 299, "def": 11}, "deep": 9, "deep_allowed": 2, "scored": 1, "missed": 0, "xpts": 2.8513, "result": "w", "date": "2021-08-14 13:30:00", "wins": 1, "draws": 0, "loses": 0, "pts": 3, "npxGD": 1.732178}]}, "132": {"id": "132", "title": "Eintracht Frankfurt", "history": [{"h_a": "a", "xG": 1.36709, "xGA": 2.83799, "npxG": 1.36709, "npxGA": 2.83799, "ppda": {"att": 411, "def": 31}, "ppda_allowed": {"att": 219, "def": 14}, "deep": 1, "deep_allowed": 17, "scored": 2, "missed": 5, "xpts": 0.5086, "result": "l", "date": "2021-08-14 16:30:00", "wins": 0, "draws": 0, "loses": 1, "pts": 0, "npxGD": -1.4709}]}, "133": {"id": "133", "title": "VfB Stuttgart", "history": [{"h_a": "h", "xG": 4.25968, "xGA": 1.31466, "npxG": 4.25968, "npxGA": 1.31466, "ppda": {"att": 204, "def": 19}, "ppda_allowed": {"att": 405, "def": 16}, "deep": 14, "deep_allowed": 3, "scored": 5, "missed": 1, "xpts": 2.7746999999999997, "result": "w", "date": "2021-08-14 13:30:00", "wins": 1, "draws": 0, "loses": 0, "pts": 3, "npxGD": 2.9450200000000004}]}, "134": {"id": "134", "title": "FC Cologne", "history": [{"h_a": "h", "xG": 1.62567, "xGA": 2.1078, "npxG": 1.62567, "npxGA": 2.1078, "ppda": {"att": 170, "def": 33}, "ppda_allowed": {"att": 242, "def": 17}, "deep": 8, "deep_allowed": 4, "scored": 3, "missed": 1, "xpts": 0.9514, "result": "w", "date": "2021-08-15 15:30:00", "wins": 1, "draws": 0, "loses": 0, "pts": 3, "npxGD": -0.48213000000000017}]}, "135": {"id": "135", "title": "Freiburg", "history": [{"h_a": "a", "xG": 1.63663, "xGA": 0.575032, "npxG": 1.63663, "npxGA": 0.575032, "ppda": {"att": 169, "def": 20}, "ppda_allowed": {"att": 226, "def": 24}, "deep": 4, "deep_allowed": 5, "scored": 0, "missed": 0, "xpts": 2.2525, "result": "d", "date": "2021-08-14 13:30:00", "wins": 0, "draws": 1, "loses": 0, "pts": 1, "npxGD": 1.061598}]}, "136": {"id": "136", "title": "RasenBallsport Leipzig", "history": [{"h_a": "a", "xG": 0.841814, "xGA": 1.27109, "npxG": 0.841814, "npxGA": 1.27109, "ppda": {"att": 106, "def": 23}, "ppda_allowed": {"att": 301, "def": 18}, "deep": 6, "deep_allowed": 2, "scored": 0, "missed": 1, "xpts": 0.8453, "result": "l", "date": "2021-08-15 13:30:00", "wins": 0, "draws": 0, "loses": 1, "pts": 0, "npxGD": -0.4292760000000001}]}, "240": {"id": "240", "title": "Union Berlin", "history": [{"h_a": "h", "xG": 0.443841, "xGA": 0.7943, "npxG": 0.443841, "npxGA": 0.7943, "ppda": {"att": 437, "def": 24}, "ppda_allowed": {"att": 172, "def": 24}, "deep": 6, "deep_allowed": 5, "scored": 1, "missed": 1, "xpts": 0.9779, "result": "d", "date": "2021-08-14 13:30:00", "wins": 0, "draws": 1, "loses": 0, "pts": 1, "npxGD": -0.350459}]}, "262": {"id": "262", "title": "Arminia Bielefeld", "history": [{"h_a": "h", "xG": 0.575032, "xGA": 1.63663, "npxG": 0.575032, "npxGA": 1.63663, "ppda": {"att": 226, "def": 24}, "ppda_allowed": {"att": 169, "def": 20}, "deep": 5, "deep_allowed": 4, "scored": 0, "missed": 0, "xpts": 0.5164, "result": "d", "date": "2021-08-14 13:30:00", "wins": 0, "draws": 1, "loses": 0, "pts": 1, "npxGD": -1.061598}]}, "267": {"id": "267", "title": "Greuther Fuerth", "history": [{"h_a": "a", "xG": 1.31466, "xGA": 4.25968, "npxG": 1.31466, "npxGA": 4.25968, "ppda": {"att": 405, "def": 16}, "ppda_allowed": {"att": 204, "def": 19}, "deep": 3, "deep_allowed": 14, "scored": 1, "missed": 5, "xpts": 0.15510000000000002, "result": "l", "date": "2021-08-14 13:30:00", "wins": 0, "draws": 0, "loses": 1, "pts": 0, "npxGD": -2.9450200000000004}]}, "268": {"id": "268", "title": "Bochum", "history": [{"h_a": "a", "xG": 0.297792, "xGA": 2.78774, "npxG": 0.297792, "npxGA": 2.02997, "ppda": {"att": 299, "def": 11}, "ppda_allowed": {"att": 166, "def": 17}, "deep": 2, "deep_allowed": 9, "scored": 0, "missed": 1, "xpts": 0.0916, "result": "l", "date": "2021-08-14 13:30:00", "wins": 0, "draws": 0, "loses": 1, "pts": 0, "npxGD": -1.732178}]}}